colab_ssh/__init__.py
colab_ssh/_command.py
colab_ssh/get_tunnel_config.py
colab_ssh/init_git.py
colab_ssh/launch_direct_ssh.py
colab_ssh/launch_ssh.py
colab_ssh/launch_ssh_cloudflared.py
colab_ssh/set_private_key.py
colab_ssh/git/__init__.py
colab_ssh/git/generic.py
colab_ssh/git/github.py
colab_ssh/git/gitlab.py
colab_ssh/ssh/__init__.py
colab_ssh/ssh/public_key.py
colab_ssh/utils/__init__.py
colab_ssh/utils/add_folder_to_sys_path.py
colab_ssh/utils/expose_env_variable.py
colab_ssh/utils/show_hint_message.py
colab_ssh/utils/auth/__init__.py
colab_ssh/utils/auth/ask_user_pass.py
colab_ssh/utils/logger/__init__.py
colab_ssh/utils/logger/logger.py
colab_ssh/utils/packages/__init__.py
colab_ssh/utils/packages/installer.py
colab_ssh/utils/ui/__init__.py
colab_ssh/utils/ui/init_git.html
colab_ssh/utils/ui/launch_ssh_cloudflared.html
colab_ssh/utils/ui/render_html.py
tests/__init__.py
tests/conftest.py
tests/test_expose_env_var.py
tests/test_init_git.py
tests/test_launch_ssh.py
tests/ngrok/__init__.py
tests/ngrok/test_ngrok_init_git.py
tests/ngrok/test_ngrok_launch_ssh.py
colab_ssh-0.3.27.dist-info/LICENSE
colab_ssh-0.3.27.dist-info/METADATA
colab_ssh-0.3.27.dist-info/WHEEL
colab_ssh-0.3.27.dist-info/top_level.txt
colab_ssh-0.3.27.dist-info/RECORD
